CONTRIBUTING.rst
HISTORY.rst
LICENSE
MANIFEST.in
README.rst
setup.cfg
setup.py
databricks_api_utils/__init__.py
databricks_api_utils/io.py
databricks_api_utils.egg-info/PKG-INFO
databricks_api_utils.egg-info/SOURCES.txt
databricks_api_utils.egg-info/dependency_links.txt
databricks_api_utils.egg-info/not-zip-safe
databricks_api_utils.egg-info/top_level.txt
docs/Makefile
docs/conf.py
docs/contributing.rst
docs/history.rst
docs/index.rst
docs/installation.rst
docs/make.bat
docs/readme.rst
docs/usage.rst
tests/__init__.py
tests/test_databricks_api_utils.py
tests/fixtures/lang_examples/dbc-test.dbc
tests/fixtures/lang_examples/html-test.html
tests/fixtures/lang_examples/jupyter-test.ipynb
tests/fixtures/lang_examples/py-test.py
tests/fixtures/lang_examples/r-test.r
tests/fixtures/lang_examples/sc-test.sc
tests/fixtures/lang_examples/scala-test.scala
tests/fixtures/lang_examples/sql-test.sql
tests/fixtures/project_example/py_example_1.py
tests/fixtures/project_example/py_example_2.py
tests/fixtures/recursion_example/py-test.py
tests/fixtures/recursion_example/subdir/py-test.py