Metadata-Version: 1.2
Name: databricks-api-utils
Version: 0.1.1
Summary: Helper functions for working with databricks-api
Home-page: https://github.com/sam-harvey/databricks_api_utils
Author: Sam Harvey
Author-email: samuel.robert.harvey@gmail.com
License: MIT license
Keywords: databricks_api_utils
Platform: UNKNOWN
Classifier: Development Status :: 2 - Pre-Alpha
Classifier: Intended Audience :: Developers
Classifier: License :: OSI Approved :: MIT License
Classifier: Natural Language :: English
Classifier: Programming Language :: Python :: 3
Classifier: Programming Language :: Python :: 3.6
Classifier: Programming Language :: Python :: 3.7
Classifier: Programming Language :: Python :: 3.8
Requires-Python: >=3.6
